{"vin":"VIN1001","data":[{"date":"2025-02-28","G-Force":0.61,"X-acc":1.03,"Y-acc":-2.27},{"date":"2025-02-27","G-Force":1.97,"X-acc":-1.18,"Y-acc":-0.72},{"date":"2025-02-26","G-Force":1.56,"X-acc":-1.1,"Y-acc":2.13},{"date":"2025-02-25","G-Force":2.35,"X-acc":2.72,"Y-acc":-0.51},{"date":"2025-02-24","G-Force":1.46,"X-acc":2.3,"Y-acc":-2.4},{"date":"2025-02-23","G-Force":1.61,"X-acc":-1.92,"Y-acc":0.23},{"date":"2025-02-22","G-Force":1.49,"X-acc":0.63,"Y-acc":2.85},{"date":"2025-02-21","G-Force":2.37,"X-acc":1.66,"Y-acc":-2.57},{"date":"2025-02-20","G-Force":2.08,"X-acc":1.94,"Y-acc":-0.45},{"date":"2025-02-19","G-Force":0.5,"X-acc":-2.61,"Y-acc":-2.72},{"date":"2025-02-18","G-Force":1.18,"X-acc":2.43,"Y-acc":1.93},{"date":"2025-02-17","G-Force":2.48,"X-acc":2.09,"Y-acc":1.34},{"date":"2025-02-16","G-Force":0.71,"X-acc":2.31,"Y-acc":1.22},{"date":"2025-02-15","G-Force":1.18,"X-acc":-2.55,"Y-acc":1.31},{"date":"2025-02-14","G-Force":2.41,"X-acc":-2.72,"Y-acc":-0.11},{"date":"2025-02-13","G-Force":1.43,"X-acc":-1.15,"Y-acc":-2.54},{"date":"2025-02-12","G-Force":1.71,"X-acc":1.95,"Y-acc":2.7},{"date":"2025-02-11","G-Force":1.53,"X-acc":-0.93,"Y-acc":-0.33},{"date":"2025-02-10","G-Force":1.78,"X-acc":2.97,"Y-acc":1.38},{"date":"2025-02-09","G-Force":1.73,"X-acc":0.51,"Y-acc":-2.34},{"date":"2025-02-08","G-Force":1.89,"X-acc":-2.72,"Y-acc":-0.82},{"date":"2025-02-07","G-Force":2.47,"X-acc":-2.12,"Y-acc":2.58},{"date":"2025-02-06","G-Force":1.08,"X-acc":-0.27,"Y-acc":0.21},{"date":"2025-02-05","G-Force":2.37,"X-acc":-0.31,"Y-acc":-2.13},{"date":"2025-02-04","G-Force":2.18,"X-acc":0.01,"Y-acc":1.99},{"date":"2025-02-03","G-Force":0.62,"X-acc":-0.75,"Y-acc":2.21},{"date":"2025-02-02","G-Force":0.59,"X-acc":0.5,"Y-acc":-0.68},{"date":"2025-02-01","G-Force":1.79,"X-acc":1.96,"Y-acc":-0.71},{"date":"2025-01-31","G-Force":2.1,"X-acc":0.65,"Y-acc":-2.2},{"date":"2025-01-30","G-Force":1.91,"X-acc":2.32,"Y-acc":1.89},{"date":"2025-01-29","G-Force":1.79,"X-acc":0.02,"Y-acc":0.76},{"date":"2025-01-28","G-Force":1.97,"X-acc":1.48,"Y-acc":0.88},{"date":"2025-01-27","G-Force":1.49,"X-acc":1.03,"Y-acc":1.99},{"date":"2025-01-26","G-Force":1.87,"X-acc":-0.52,"Y-acc":-1.93},{"date":"2025-01-25","G-Force":0.91,"X-acc":-1.06,"Y-acc":0.33},{"date":"2025-01-24","G-Force":1.67,"X-acc":2.2,"Y-acc":1.48},{"date":"2025-01-23","G-Force":1.75,"X-acc":0.11,"Y-acc":1.46},{"date":"2025-01-22","G-Force":0.72,"X-acc":-1.09,"Y-acc":1.69},{"date":"2025-01-21","G-Force":2.32,"X-acc":1.24,"Y-acc":-1.8},{"date":"2025-01-20","G-Force":1.67,"X-acc":1.62,"Y-acc":-1.51},{"date":"2025-01-19","G-Force":1.69,"X-acc":-2.66,"Y-acc":1.64},{"date":"2025-01-18","G-Force":1.05,"X-acc":2.54,"Y-acc":-1.52},{"date":"2025-01-17","G-Force":1.57,"X-acc":-1.34,"Y-acc":-0.71},{"date":"2025-01-16","G-Force":1.99,"X-acc":-1.74,"Y-acc":1.09},{"date":"2025-01-15","G-Force":1.51,"X-acc":1.41,"Y-acc":2.15},{"date":"2025-01-14","G-Force":2.46,"X-acc":1.58,"Y-acc":-1.12},{"date":"2025-01-13","G-Force":2.25,"X-acc":2.51,"Y-acc":-2.91},{"date":"2025-01-12","G-Force":1.9,"X-acc":-0.6,"Y-acc":2.48},{"date":"2025-01-11","G-Force":1.95,"X-acc":0.23,"Y-acc":2.59},{"date":"2025-01-10","G-Force":2.08,"X-acc":2.08,"Y-acc":2.42},{"date":"2025-01-09","G-Force":1.35,"X-acc":-0.59,"Y-acc":0.33},{"date":"2025-01-08","G-Force":1.2,"X-acc":-2.03,"Y-acc":1.49},{"date":"2025-01-07","G-Force":1.11,"X-acc":0.72,"Y-acc":-1.19},{"date":"2025-01-06","G-Force":0.59,"X-acc":1.93,"Y-acc":2.59},{"date":"2025-01-05","G-Force":1.51,"X-acc":-2.74,"Y-acc":0.23},{"date":"2025-01-04","G-Force":2.06,"X-acc":1.12,"Y-acc":-2.2},{"date":"2025-01-03","G-Force":1.75,"X-acc":-0.29,"Y-acc":-0.78},{"date":"2025-01-02","G-Force":1.07,"X-acc":2.91,"Y-acc":1.38},{"date":"2025-01-01","G-Force":2.18,"X-acc":-1.69,"Y-acc":-0.53},{"date":"2024-12-31","G-Force":1.24,"X-acc":-0.34,"Y-acc":-0.95},{"date":"2024-12-30","G-Force":1.74,"X-acc":2.04,"Y-acc":2.57},{"date":"2024-12-29","G-Force":1.64,"X-acc":-1.17,"Y-acc":0.56},{"date":"2024-12-28","G-Force":1.62,"X-acc":0.87,"Y-acc":-1.17},{"date":"2024-12-27","G-Force":0.94,"X-acc":1.75,"Y-acc":1.45},{"date":"2024-12-26","G-Force":0.55,"X-acc":-2.28,"Y-acc":-0.68},{"date":"2024-12-25","G-Force":0.97,"X-acc":1.88,"Y-acc":1.55},{"date":"2024-12-24","G-Force":0.84,"X-acc":2.23,"Y-acc":-1.02},{"date":"2024-12-23","G-Force":1.51,"X-acc":-1.37,"Y-acc":1.18},{"date":"2024-12-22","G-Force":2.15,"X-acc":1.9,"Y-acc":-2.9},{"date":"2024-12-21","G-Force":0.85,"X-acc":2.19,"Y-acc":0.43},{"date":"2024-12-20","G-Force":1.56,"X-acc":0.03,"Y-acc":-2.4},{"date":"2024-12-19","G-Force":1.95,"X-acc":-1.31,"Y-acc":-1.66},{"date":"2024-12-18","G-Force":0.85,"X-acc":-2.96,"Y-acc":-1.23},{"date":"2024-12-17","G-Force":0.52,"X-acc":-2.49,"Y-acc":-2.2},{"date":"2024-12-16","G-Force":1.31,"X-acc":-0.97,"Y-acc":-2.91},{"date":"2024-12-15","G-Force":1.87,"X-acc":-2.97,"Y-acc":-2.38},{"date":"2024-12-14","G-Force":1.89,"X-acc":-2.97,"Y-acc":-0.4},{"date":"2024-12-13","G-Force":0.64,"X-acc":2.6,"Y-acc":0.8},{"date":"2024-12-12","G-Force":0.81,"X-acc":2.7,"Y-acc":2.85},{"date":"2024-12-11","G-Force":2.43,"X-acc":0.31,"Y-acc":2.17},{"date":"2024-12-10","G-Force":2.06,"X-acc":-2.23,"Y-acc":1.09},{"date":"2024-12-09","G-Force":0.89,"X-acc":-1.83,"Y-acc":-0.72},{"date":"2024-12-08","G-Force":0.87,"X-acc":1.23,"Y-acc":2.81},{"date":"2024-12-07","G-Force":2.44,"X-acc":-0.61,"Y-acc":1.94},{"date":"2024-12-06","G-Force":0.88,"X-acc":-2.21,"Y-acc":-0.61},{"date":"2024-12-05","G-Force":1.39,"X-acc":-2.8,"Y-acc":1.37},{"date":"2024-12-04","G-Force":1.07,"X-acc":-1.62,"Y-acc":0.71},{"date":"2024-12-03","G-Force":2.01,"X-acc":-1.65,"Y-acc":-2.24},{"date":"2024-12-02","G-Force":0.76,"X-acc":2.75,"Y-acc":2.25},{"date":"2024-12-01","G-Force":0.66,"X-acc":2.03,"Y-acc":-2.4},{"date":"2024-11-30","G-Force":1.49,"X-acc":-0.97,"Y-acc":-0.89},{"date":"2024-11-29","G-Force":1.73,"X-acc":-1.73,"Y-acc":1.08},{"date":"2024-11-28","G-Force":0.59,"X-acc":0.07,"Y-acc":1.28},{"date":"2024-11-27","G-Force":2.15,"X-acc":1.06,"Y-acc":-0.2},{"date":"2024-11-26","G-Force":2.3,"X-acc":-0.34,"Y-acc":2.65},{"date":"2024-11-25","G-Force":0.97,"X-acc":2.68,"Y-acc":0.42},{"date":"2024-11-24","G-Force":2.39,"X-acc":-1.01,"Y-acc":0.93},{"date":"2024-11-23","G-Force":2.38,"X-acc":-0.56,"Y-acc":-2.44},{"date":"2024-11-22","G-Force":1.86,"X-acc":-2.14,"Y-acc":0.89},{"date":"2024-11-21","G-Force":1.13,"X-acc":-2.02,"Y-acc":2.31},{"date":"2024-11-20","G-Force":1.71,"X-acc":-1.55,"Y-acc":-3.0},{"date":"2024-11-19","G-Force":2.32,"X-acc":0.06,"Y-acc":1.92},{"date":"2024-11-18","G-Force":2.2,"X-acc":-1.95,"Y-acc":2.0},{"date":"2024-11-17","G-Force":1.52,"X-acc":2.12,"Y-acc":-0.35},{"date":"2024-11-16","G-Force":0.56,"X-acc":-0.29,"Y-acc":-0.82},{"date":"2024-11-15","G-Force":2.19,"X-acc":-1.5,"Y-acc":0.58},{"date":"2024-11-14","G-Force":2.19,"X-acc":-2.68,"Y-acc":1.98},{"date":"2024-11-13","G-Force":1.79,"X-acc":-2.88,"Y-acc":2.14},{"date":"2024-11-12","G-Force":1.26,"X-acc":1.43,"Y-acc":-1.59},{"date":"2024-11-11","G-Force":1.37,"X-acc":-2.35,"Y-acc":1.26},{"date":"2024-11-10","G-Force":1.72,"X-acc":-1.58,"Y-acc":1.31},{"date":"2024-11-09","G-Force":0.53,"X-acc":0.77,"Y-acc":1.45},{"date":"2024-11-08","G-Force":0.86,"X-acc":-1.06,"Y-acc":-2.91},{"date":"2024-11-07","G-Force":1.55,"X-acc":0.82,"Y-acc":0.88},{"date":"2024-11-06","G-Force":0.96,"X-acc":-2.73,"Y-acc":-0.88},{"date":"2024-11-05","G-Force":2.09,"X-acc":-0.14,"Y-acc":0.56},{"date":"2024-11-04","G-Force":1.28,"X-acc":1.84,"Y-acc":-2.75},{"date":"2024-11-03","G-Force":1.55,"X-acc":2.15,"Y-acc":-1.54},{"date":"2024-11-02","G-Force":2.03,"X-acc":2.06,"Y-acc":-1.77},{"date":"2024-11-01","G-Force":1.88,"X-acc":1.07,"Y-acc":-1.96},{"date":"2024-10-31","G-Force":0.69,"X-acc":1.97,"Y-acc":-2.89},{"date":"2024-10-30","G-Force":0.85,"X-acc":-1.01,"Y-acc":-0.65},{"date":"2024-10-29","G-Force":1.5,"X-acc":-1.3,"Y-acc":2.5},{"date":"2024-10-28","G-Force":1.12,"X-acc":2.1,"Y-acc":0.94},{"date":"2024-10-27","G-Force":1.43,"X-acc":1.32,"Y-acc":-2.82},{"date":"2024-10-26","G-Force":1.96,"X-acc":2.06,"Y-acc":-2.25},{"date":"2024-10-25","G-Force":0.52,"X-acc":1.29,"Y-acc":1.14},{"date":"2024-10-24","G-Force":0.58,"X-acc":-0.55,"Y-acc":-0.57},{"date":"2024-10-23","G-Force":0.92,"X-acc":1.85,"Y-acc":2.97},{"date":"2024-10-22","G-Force":0.63,"X-acc":-1.06,"Y-acc":1.5},{"date":"2024-10-21","G-Force":2.03,"X-acc":0.98,"Y-acc":2.24},{"date":"2024-10-20","G-Force":1.85,"X-acc":0.86,"Y-acc":1.02},{"date":"2024-10-19","G-Force":0.73,"X-acc":0.47,"Y-acc":1.72},{"date":"2024-10-18","G-Force":2.02,"X-acc":2.42,"Y-acc":2.01},{"date":"2024-10-17","G-Force":2.3,"X-acc":1.18,"Y-acc":2.57},{"date":"2024-10-16","G-Force":2.14,"X-acc":-2.8,"Y-acc":-1.56},{"date":"2024-10-15","G-Force":0.99,"X-acc":-2.21,"Y-acc":-0.54},{"date":"2024-10-14","G-Force":1.08,"X-acc":-2.72,"Y-acc":0.69},{"date":"2024-10-13","G-Force":1.73,"X-acc":2.34,"Y-acc":2.79},{"date":"2024-10-12","G-Force":1.45,"X-acc":-2.79,"Y-acc":-1.16},{"date":"2024-10-11","G-Force":1.09,"X-acc":2.96,"Y-acc":2.06},{"date":"2024-10-10","G-Force":2.15,"X-acc":-2.76,"Y-acc":2.68},{"date":"2024-10-09","G-Force":1.66,"X-acc":-0.08,"Y-acc":2.95},{"date":"2024-10-08","G-Force":1.35,"X-acc":2.64,"Y-acc":2.31},{"date":"2024-10-07","G-Force":1.2,"X-acc":-1.6,"Y-acc":-2.17},{"date":"2024-10-06","G-Force":1.38,"X-acc":-2.78,"Y-acc":-1.55},{"date":"2024-10-05","G-Force":0.86,"X-acc":-2.05,"Y-acc":1.21},{"date":"2024-10-04","G-Force":1.49,"X-acc":2.64,"Y-acc":0.39},{"date":"2024-10-03","G-Force":0.53,"X-acc":-1.87,"Y-acc":-2.21},{"date":"2024-10-02","G-Force":0.59,"X-acc":1.07,"Y-acc":2.38},{"date":"2024-10-01","G-Force":1.76,"X-acc":2.72,"Y-acc":1.5},{"date":"2024-09-30","G-Force":0.84,"X-acc":-0.42,"Y-acc":-0.94},{"date":"2024-09-29","G-Force":2.3,"X-acc":-0.13,"Y-acc":1.17},{"date":"2024-09-28","G-Force":1.08,"X-acc":2.56,"Y-acc":-0.17},{"date":"2024-09-27","G-Force":1.29,"X-acc":0.44,"Y-acc":1.99},{"date":"2024-09-26","G-Force":1.26,"X-acc":-1.57,"Y-acc":-0.4},{"date":"2024-09-25","G-Force":1.62,"X-acc":2.29,"Y-acc":-1.94},{"date":"2024-09-24","G-Force":1.37,"X-acc":0.1,"Y-acc":0.68},{"date":"2024-09-23","G-Force":0.6,"X-acc":1.48,"Y-acc":2.28},{"date":"2024-09-22","G-Force":1.8,"X-acc":0.12,"Y-acc":-0.92},{"date":"2024-09-21","G-Force":1.81,"X-acc":-2.25,"Y-acc":-0.37},{"date":"2024-09-20","G-Force":1.9,"X-acc":2.62,"Y-acc":-1.55},{"date":"2024-09-19","G-Force":1.89,"X-acc":1.69,"Y-acc":-2.89},{"date":"2024-09-18","G-Force":2.28,"X-acc":-2.24,"Y-acc":0.16},{"date":"2024-09-17","G-Force":1.32,"X-acc":1.53,"Y-acc":-1.36},{"date":"2024-09-16","G-Force":1.71,"X-acc":1.95,"Y-acc":0.74},{"date":"2024-09-15","G-Force":0.68,"X-acc":-0.53,"Y-acc":-0.65},{"date":"2024-09-14","G-Force":1.02,"X-acc":1.95,"Y-acc":-0.67},{"date":"2024-09-13","G-Force":1.9,"X-acc":-1.34,"Y-acc":-1.72},{"date":"2024-09-12","G-Force":1.87,"X-acc":2.11,"Y-acc":-1.56},{"date":"2024-09-11","G-Force":2.5,"X-acc":2.48,"Y-acc":-2.72},{"date":"2024-09-10","G-Force":0.79,"X-acc":-1.59,"Y-acc":1.45},{"date":"2024-09-09","G-Force":1.12,"X-acc":0.62,"Y-acc":1.9},{"date":"2024-09-08","G-Force":1.13,"X-acc":-2.97,"Y-acc":0.59},{"date":"2024-09-07","G-Force":1.28,"X-acc":-1.97,"Y-acc":-0.57},{"date":"2024-09-06","G-Force":1.82,"X-acc":-1.3,"Y-acc":-0.15},{"date":"2024-09-05","G-Force":1.32,"X-acc":0.85,"Y-acc":1.68},{"date":"2024-09-04","G-Force":2.36,"X-acc":-0.06,"Y-acc":1.15},{"date":"2024-09-03","G-Force":0.58,"X-acc":0.74,"Y-acc":1.15},{"date":"2024-09-02","G-Force":1.45,"X-acc":0.98,"Y-acc":1.76}]}